AUTHORS
LICENSE
MANIFEST.in
README.md
setup.py
sxxexx/__init__.py
sxxexx/sxxexx.py
sxxexx.egg-info/PKG-INFO
sxxexx.egg-info/SOURCES.txt
sxxexx.egg-info/dependency_links.txt
sxxexx.egg-info/entry_points.txt
sxxexx.egg-info/requires.txt
sxxexx.egg-info/top_level.txt