Metadata-Version: 1.1
Name: sxxexx
Version: 0.4
Summary: A command line tool to search (and download) series from the Piracy Bay
Home-page: https://github.com/nicolargo/sxxexx
Author: Nicolas Hennion
Author-email: nicolas@nicolargo.com
License: MIT
Keywords: torrent search download serie
Platform: UNKNOWN
Classifier: Development Status :: 4 - Beta
Classifier: License :: OSI Approved :: MIT License
Classifier: Programming Language :: Python :: 2
Classifier: Environment :: Console
